reflex_google_auth/__init__.py
reflex_google_auth/decorator.py
reflex_google_auth/google_auth.py
reflex_google_auth/state.py
reflex_google_auth-0.1.1.dist-info/METADATA
reflex_google_auth-0.1.1.dist-info/WHEEL
reflex_google_auth-0.1.1.dist-info/top_level.txt
reflex_google_auth-0.1.1.dist-info/RECORD
