Metadata-Version: 2.2
Name: reflex-google-auth
Version: 0.1.1
Summary: Sign in with Google
Author-email: Masen Furer <m_github@0x26.net>
License: Apache-2.0
Project-URL: homepage, https://github.com/masenf/reflex-google-auth
Keywords: reflex,reflex-custom-components
Classifier: Development Status :: 4 - Beta
Requires-Python: >=3.10
Requires-Dist: reflex>=0.7.0a2
Requires-Dist: google-auth[requests]
Provides-Extra: dev
Requires-Dist: build; extra == "dev"
Requires-Dist: twine; extra == "dev"
